{
    "SAMSUNG": "Samsung Electronics Co., Ltd.",
    "TCL": "TCL Electronics Holdings Ltd.",
    "LG": "LG Electronics, Inc.",
    "PHILIPS": "Koninklijke Philips NV",
    "BOSH": "Robert Bosch GmbH",
    "HISENSE": "Hisense Home Appliances Group Co., Ltd.",
    "ASUS": "ASUSTek Computer, Inc.",
    "EPSON": "Seiko Epson Corp.",
    "MSI": "Motorola Solutions, Inc.",
    "DELL": "Dell Technologies, Inc.",
    "BROTHER": "Brother Industries, Ltd.",
    "BOSCH": "Bosch Ltd.",
    "BEKO": "Arçelik AS",
    "ACER": "Acer, Inc.",
    "CANON": "Canon Electronics, Inc.",
    "CANDY" : "Haier Smart Home Co., Ltd.",
    "WHIRLPOOL": "Whirlpool Corp.",
    "HISENSE": "Hisense Home Appliances Group Co., Ltd.",
    "LENOVO": "Lenovo Group Ltd.",
    "ROWENTA": "SEB SA",
    "BRAUN": "Procter & Gamble Co.",
    "SONY": "Sony Group Corp.",
    "ELECTROLUX": "Electrolux AB",
    "HAIER": "Haier Smart Home Co., Ltd.",
    "SMEG": "SMEG SPA",
    "HOOVER": "Haier Smart Home Co., Ltd.",
    "HP": "Hewlett Packard Enterprise Co.",
    "SIEMENS": "Siemens Energy AG",
    "INDESIT": "Whirlpool Corp.",
    "TEFAL": "SEB SA",
    "SHARP" : "Sharp Corp.",
    "PREWAVE": "PREWAVE GMBH",
    "BENQ": "Qisda Corp.",
    "THOMSON": "Thomson Reuters Corp.",
    "PANASONIC": "Panasonic Holdings Corp.",
    "FUJITSU": "Fujitsu General Ltd.",
    "NINTENDO": "Nintendo Co., Ltd.",
    "ADLER": "Stadler Rail AG",
    "Salton Inc": "Spectrum Brands Holdings, Inc.",
    "XIAOMI": "Xiaomi Corp.",
    "LEXMARK": "International Business Machines Corp.",
    "CONTINENTAL EDISON": "Casino, Guichard-Perrachon SA",
    "HOTPOINT": "Arçelik AS",
    "MEDION": "Lenovo Group Ltd.",
    "KARCHER": "KSB SE & Co. KGaA",
    "GIGABYTE": "Gigabyte Technology Co., Ltd.",
    "ZEBRA": "Zebra Technologies Corp.",
    "SCHNEIDER": "Schneider Electric SE",
    "KRUPS": "SEB SA",
    "BLACK & DECKER": "Stanley Black & Decker, Inc.",
    "MICROSOFT": "Microsoft Corp.",
    "GRUNDIG": "Arçelik AS",
    "DOMO": "Domo, Inc.",
    "DATALOGIC": "Datalogic SpA",
    "TOSHIBA": "Toshiba Tec Corp.",
    "RICOH": "Ricoh Co., Ltd.",
    "HONEYWELL": "Honeywell International, Inc.",
    "NILFISK": "Nilfisk Holding A/S",
    "MOULINEX": "SEB SA",
    "KYOCERA": "Kyocera Corp.",
    "KITCHENAID": "Whirlpool Corp.",
    "YONIS" : "DaikyoNishikawa Corp.",
    "IROBOT": "iRobot Corp.",
    "STAR MICRONICS": "Star Micronics Co., Ltd.",
    "YAMAHA": "Yamaha Corp.",
    "JVC": "JVCKenwood Corp.",
    "APPLE": "Apple, Inc.",
    "XGIMI" : "XGimi Technology Co., Ltd."
    "CITIZEN" : "Citizen Watch Co., Ltd.",
    "TAURUS": "Taurus Armas SA",
    "SMART TECH": "Hainan Jinpan Smart Technology Co., Ltd."
}
